serializedb.py
serializeDB-0.0.1.dist-info/LICENSE
serializeDB-0.0.1.dist-info/METADATA
serializeDB-0.0.1.dist-info/WHEEL
serializeDB-0.0.1.dist-info/top_level.txt
serializeDB-0.0.1.dist-info/RECORD
