Metadata-Version: 2.1
Name: serializeDB
Version: 0.0.1
Summary: A lightweight key-value database based on serialization
Home-page: https://github.com/imyizhang/serializeDB
Author: Yi Zhang
Author-email: yizhang.dev@gmail.com
License: three-clause BSD
Download-URL: https://github.com/imyizhang/serializeDB
Keywords: key-value,database,serialization
Platform: UNKNOWN
Classifier: License :: OSI Approved :: BSD License
Classifier: Operating System :: OS Independent
Classifier: Programming Language :: Python :: 3
License-File: LICENSE
